dictid/__init__.py
dictid/base62.py
dictid/dict.py
dictid-0.2102.1.dist-info/WHEEL
dictid-0.2102.1.dist-info/METADATA
dictid-0.2102.1.dist-info/RECORD
